{"name":"Municipalities of Cape Verde","regions":"Municipalities","href":"/wiki/Category:Municipalities_of_Cape_Verde","Municipalities":[{"name":"Boa Vista, Cape Verde","href":"/wiki/Category:Boa_Vista,_Cape_Verde"},{"name":"Brava Municipality","href":"/wiki/Category:Brava_Municipality"},{"name":"Maio, Cape Verde","href":"/wiki/Category:Maio,_Cape_Verde"},{"name":"Mosteiros, Cape Verde","href":"/wiki/Category:Mosteiros,_Cape_Verde"},{"name":"Paul, Cape Verde","href":"/wiki/Category:Paul,_Cape_Verde"},{"name":"Porto Novo Municipality","href":"/wiki/Category:Porto_Novo_Municipality"},{"name":"Praia","href":"/wiki/Category:Praia"},{"name":"Ribeira Brava, Cape Verde","href":"/wiki/Category:Ribeira_Brava,_Cape_Verde"},{"name":"Ribeira Grande de Santiago","href":"/wiki/Category:Ribeira_Grande_de_Santiago"},{"name":"Ribeira Grande Municipality","href":"/wiki/Category:Ribeira_Grande_Municipality"},{"name":"Sal, Cape Verde","href":"/wiki/Category:Sal,_Cape_Verde"},{"name":"Santa Catarina do Fogo","href":"/wiki/Category:Santa_Catarina_do_Fogo"},{"name":"Santa Catarina, Cape Verde","href":"/wiki/Category:Santa_Catarina,_Cape_Verde"},{"name":"Santa Cruz, Cape Verde","href":"/wiki/Category:Santa_Cruz,_Cape_Verde"},{"name":"São Domingos Municipality, Cape Verde","href":"/wiki/Category:S%C3%A3o_Domingos_Municipality,_Cape_Verde"},{"name":"São Filipe, Cape Verde","href":"/wiki/Category:S%C3%A3o_Filipe,_Cape_Verde"},{"name":"São Lourenço dos Órgãos","href":"/wiki/Category:S%C3%A3o_Louren%C3%A7o_dos_%C3%93rg%C3%A3os"},{"name":"São Miguel, Cape Verde","href":"/wiki/Category:S%C3%A3o_Miguel,_Cape_Verde"},{"name":"São Salvador do Mundo, Cape Verde","href":"/wiki/Category:S%C3%A3o_Salvador_do_Mundo,_Cape_Verde"},{"name":"São Vicente Municipality","href":"/wiki/Category:S%C3%A3o_Vicente_Municipality"},{"name":"Tarrafal de São Nicolau","href":"/wiki/Category:Tarrafal_de_S%C3%A3o_Nicolau"},{"name":"Tarrafal Municipality","href":"/wiki/Category:Tarrafal_Municipality"}]}