{"name":"Provinces of Pakistan","regions":"Provinces","href":"/wiki/Category:Provinces_of_Pakistan","Provinces":[null,{"name":"Balochistan, Pakistan","href":"/wiki/Category:Balochistan,_Pakistan"},{"name":"Khyber Pakhtunkhwa","href":"/wiki/Category:Khyber_Pakhtunkhwa"},{"name":"Proposed provinces and territories of Pakistan","href":"/wiki/Category:Proposed_provinces_and_territories_of_Pakistan"},{"name":"Provincial disputes in Pakistan","href":"/wiki/Category:Provincial_disputes_in_Pakistan"},{"name":"Provincially Administered Tribal Areas","href":"/wiki/Category:Provincially_Administered_Tribal_Areas"},{"name":"Punjab, Pakistan","href":"/wiki/Category:Punjab,_Pakistan"},{"name":"Sindh","href":"/wiki/Category:Sindh"}]}